esockets
