Metadata-Version: 1.1
Name: esockets
Version: 3.0.5
Summary: A socket server
Home-page: https://github.com/Zaeb0s/epoll-socket-server
Author: Christoffer Zakrisson
Author-email: christoffer_zakrisson@hotmail.com
License: MIT
Keywords: socket,epoll,server,poll,select,TCP,web,esockets
Platform: UNKNOWN
Classifier: Development Status :: 4 - Beta
Classifier: Programming Language :: Python :: 3.5
Classifier: Operating System :: POSIX :: Linux
Classifier: License :: OSI Approved :: MIT License
